{"status": "ok", "data": {"aqi": 15, "idx": 13457, "attributions": [{"url": "https://luftkvalitet.nilu.no/", "name": "NILU - Norsk institutt for Luftforskning (Norwegian Institute for Air Research)", "logo": "Norway-Luftkvalitet.png"}, {"url": "https://waqi.info/", "name": "World Air Quality Index Project"}], "city": {"geo": [59.903095, 10.758408], "name": "Loallmenningen, Oslo, Norway", "url": "https://aqicn.org/city/norway/norway/oslo/loallmenningen", "location": ""}, "dominentpol": "pm25", "iaqi": {"h": {"v": 82.3}, "no2": {"v": 4.5}, "p": {"v": 1008.7}, "pm10": {"v": 5}, "pm25": {"v": 15}, "t": {"v": 11.6}, "w": {"v": 0.6}, "wg": {"v": 0.1}}, "time": {"s": "2022-09-05 04:00:00", "tz": "+02:00", "v": 1662350400, "iso": "2022-09-05T04:00:00+02:00"}, "forecast": {"daily": {"o3": [{"avg": 14, "day": "2022-09-04", "max": 22, "min": 10}, {"avg": 19, "day": "2022-09-05", "max": 31, "min": 12}, {"avg": 19, "day": "2022-09-06", "max": 34, "min": 9}, {"avg": 18, "day": "2022-09-07", "max": 35, "min": 10}, {"avg": 16, "day": "2022-09-08", "max": 16, "min": 15}], "pm10": [{"avg": 6, "day": "2022-09-04", "max": 8, "min": 4}, {"avg": 8, "day": "2022-09-05", "max": 10, "min": 5}, {"avg": 9, "day": "2022-09-06", "max": 13, "min": 5}, {"avg": 10, "day": "2022-09-07", "max": 14, "min": 5}, {"avg": 11, "day": "2022-09-08", "max": 11, "min": 9}], "pm25": [{"avg": 19, "day": "2022-09-04", "max": 27, "min": 11}, {"avg": 26, "day": "2022-09-05", "max": 40, "min": 15}, {"avg": 32, "day": "2022-09-06", "max": 51, "min": 14}, {"avg": 35, "day": "2022-09-07", "max": 53, "min": 17}, {"avg": 42, "day": "2022-09-08", "max": 42, "min": 30}], "uvi": [{"avg": 0, "day": "2022-09-04", "max": 2, "min": 0}, {"avg": 0, "day": "2022-09-05", "max": 2, "min": 0}, {"avg": 0, "day": "2022-09-06", "max": 3, "min": 0}, {"avg": 0, "day": "2022-09-07", "max": 3, "min": 0}, {"avg": 0, "day": "2022-09-08", "max": 2, "min": 0}, {"avg": 1, "day": "2022-09-09", "max": 2, "min": 0}]}}, "debug": {"sync": "2022-09-05T11:23:01+09:00"}}}